LICENSE
MANIFEST.in
README.rst
setup.py
django_offline.egg-info/PKG-INFO
django_offline.egg-info/SOURCES.txt
django_offline.egg-info/dependency_links.txt
django_offline.egg-info/top_level.txt
offline/__init__.py
offline/admin.py
offline/middleware.py
offline/models.py
offline/offline.py
offline/views.py
offline/templates/admin_notification.html
offline/templates/offline.html