Metadata-Version: 1.1
Name: django-offline
Version: 0.1
Summary: A simple Django app to swith your Django project between offline/online mode and display a 503 error page, while your django site is offline (under maintenance)
Home-page: https://github.com/ankitjaiswal07/django-offline
Author: Ankit Jaiswal
Author-email: ankit.jaiswal07@gmail.com
License: BSD License
Platform: UNKNOWN
Classifier: Environment :: Web Environment
Classifier: Framework :: Django
Classifier: Intended Audience :: Developers
Classifier: License :: OSI Approved :: BSD License
Classifier: Operating System :: OS Independent
Classifier: Programming Language :: Python
Classifier: Programming Language :: Python :: 2.6
Classifier: Programming Language :: Python :: 2.7
Classifier: Topic :: Internet :: WWW/HTTP
Classifier: Topic :: Internet :: WWW/HTTP :: Dynamic Content
